palhm/__init__.py
palhm/__main__.py
palhm/exceptions.py
palhm/conf/crontab
palhm/conf/palhm-boot-report.service
palhm/conf/py-debug/aws.jsonc
palhm/conf/py-debug/localfs.jsonc
palhm/conf/py-debug/null.jsonc
palhm/conf/py-debug/palhm.jsonc
palhm/conf/py-debug/conf.d/core.json
palhm/conf/py-sample/sample.jsonc
palhm/mod/__init__.py
palhm/mod/aws.py
palhm-0.0.3.dist-info/METADATA
palhm-0.0.3.dist-info/WHEEL
palhm-0.0.3.dist-info/licenses/COPYING
palhm-0.0.3.dist-info/RECORD
