Metadata-Version: 2.4
Name: palhm
Version: 0.0.3
Summary: PALHM
Project-URL: Homepage, https://github.com/dxdxdt/PALHM/
Project-URL: Issues, https://github.com/dxdxdt/PALHM/issues
Author-email: David Timber <dxdt@dev.snart.me>
License-File: COPYING
Classifier: License :: OSI Approved :: Apache Software License
Classifier: Operating System :: OS Independent
Classifier: Programming Language :: Python :: 3
Requires-Python: >=3.9
Requires-Dist: pyjson5
Provides-Extra: aws
Requires-Dist: awscli; extra == 'aws'
Requires-Dist: boto3; extra == 'aws'
